README.md
setup.py
collaborativefilteringimplicit/__init__.py
collaborativefilteringimplicit.egg-info/PKG-INFO
collaborativefilteringimplicit.egg-info/SOURCES.txt
collaborativefilteringimplicit.egg-info/dependency_links.txt
collaborativefilteringimplicit.egg-info/not-zip-safe
collaborativefilteringimplicit.egg-info/top_level.txt